dumpty/__init__.py
dumpty/agent_detector.py
dumpty/cli.py
dumpty/downloader.py
dumpty/installer.py
dumpty/lockfile.py
dumpty/models.py
dumpty/utils.py
dumpty/agents/__init__.py
dumpty/agents/aider.py
dumpty/agents/base.py
dumpty/agents/claude.py
dumpty/agents/cline.py
dumpty/agents/continue_agent.py
dumpty/agents/copilot.py
dumpty/agents/cursor.py
dumpty/agents/gemini.py
dumpty/agents/opencode.py
dumpty/agents/registry.py
dumpty/agents/windsurf.py
prompty_dumpty-0.7.0.dist-info/licenses/LICENSE
prompty_dumpty-0.7.0.dist-info/METADATA
prompty_dumpty-0.7.0.dist-info/WHEEL
prompty_dumpty-0.7.0.dist-info/entry_points.txt
prompty_dumpty-0.7.0.dist-info/top_level.txt
prompty_dumpty-0.7.0.dist-info/RECORD
