Metadata-Version: 2.4
Name: prompty-dumpty
Version: 0.7.0
Summary: Universal package manager for AI coding assistants
Author-email: Dasith Wijesiriwardena <git@dasith.me>
License: MIT
Project-URL: Homepage, https://dumpty.dev
Project-URL: Documentation, https://dumpty.dev/docs
Project-URL: Repository, https://github.com/dasiths/PromptyDumpty
Project-URL: Issues, https://github.com/dasiths/PromptyDumpty/issues
Keywords: ai,prompts,package-manager,copilot,claude,cursor
Classifier: Development Status :: 3 - Alpha
Classifier: Intended Audience :: Developers
Classifier: License :: OSI Approved :: MIT License
Classifier: Programming Language :: Python :: 3
Classifier: Programming Language :: Python :: 3.8
Classifier: Programming Language :: Python :: 3.9
Classifier: Programming Language :: Python :: 3.10
Classifier: Programming Language :: Python :: 3.11
Classifier: Programming Language :: Python :: 3.12
Requires-Python: >=3.8
License-File: LICENSE
Requires-Dist: click>=8.0
Requires-Dist: PyYAML>=6.0
Requires-Dist: rich>=10.0
Requires-Dist: packaging>=20.0
Provides-Extra: dev
Requires-Dist: pytest>=7.0; extra == "dev"
Requires-Dist: pytest-cov>=4.0; extra == "dev"
Requires-Dist: black>=23.0; extra == "dev"
Requires-Dist: ruff>=0.1.0; extra == "dev"
Requires-Dist: mypy>=1.0; extra == "dev"
Dynamic: license-file
